dagdshort/__init__.py
dagdshort/config.py
dagdshort/exc.py
dagdshort/shortener.py
dagdshort-0.2.0.dist-info/LICENSE
dagdshort-0.2.0.dist-info/METADATA
dagdshort-0.2.0.dist-info/WHEEL
dagdshort-0.2.0.dist-info/top_level.txt
dagdshort-0.2.0.dist-info/RECORD
