Metadata-Version: 2.1
Name: dagdshort
Version: 0.2.0
Summary: Multithreaded concurrent da.gd URL shortener with in-memory cache
Home-page: https://github.com/impredicative/dagdshort/
Author: Ouroboros Chrysopoeia
Author-email: impredicative@users.nomail.github.com
Keywords: da.gd url shortener
Classifier: Programming Language :: Python :: 3.9
Classifier: Programming Language :: Python :: 3.10
Classifier: Programming Language :: Python :: 3.11
Classifier: License :: OSI Approved :: GNU Affero General Public License v3
Classifier: Topic :: Internet :: WWW/HTTP
Classifier: Topic :: Software Development :: Libraries :: Python Modules
Requires-Python: >=3.9
License-File: LICENSE
Requires-Dist: requests (>=2.28.1)
